randomish_port.py
randomish_port-0.1.2.dist-info/licenses/LICENSE
randomish_port-0.1.2.dist-info/METADATA
randomish_port-0.1.2.dist-info/WHEEL
randomish_port-0.1.2.dist-info/entry_points.txt
randomish_port-0.1.2.dist-info/top_level.txt
randomish_port-0.1.2.dist-info/RECORD
