Metadata-Version: 2.4
Name: randomish-port
Version: 0.1.2
Summary: Small Python script to generate a randomish unregistered port
License-Expression: Apache-2.0
Project-URL: Homepage, https://github.com/ctengel/randomish-port
Classifier: Programming Language :: Python :: 3
Classifier: Operating System :: OS Independent
Requires-Python: >=3.0
License-File: LICENSE
Requires-Dist: requests
Dynamic: license-file
